umdsubmit/.DS_Store
umdsubmit/submit.py
umdsubmit-1.4.2.dist-info/LICENSE
umdsubmit-1.4.2.dist-info/METADATA
umdsubmit-1.4.2.dist-info/WHEEL
umdsubmit-1.4.2.dist-info/entry_points.txt
umdsubmit-1.4.2.dist-info/RECORD
